MANIFEST.in
README.md
setup.cfg
setup.py
onatlib/channel.py
onatlib/signaling_share_ws.py
onatlib.egg-info/PKG-INFO
onatlib.egg-info/SOURCES.txt
onatlib.egg-info/dependency_links.txt
onatlib.egg-info/entry_points.txt
onatlib.egg-info/not-zip-safe
onatlib.egg-info/requires.txt
onatlib.egg-info/top_level.txt
tools/__init__.py
tools/echo_test.py
tools/hoge.py
tools/hogehoge1.py
tools/hogehoge2.py
tools/p2p_com_local_server.py
tools/pync.py
tools/pync_shutdown.py
tools/rkan.py
tools/rkan3.py
tools/rkan4.py
tools/seedchanged.py
tools/sf.py
tools/sharable-ws-filexfe-use-same-transport.py
tools/sharable-ws-filexfer-keep-no-send.py
tools/sharable-ws-filexfer-ping-poing-seriarized-pc-generataion.py
tools/sharable-ws-filexfer-ping-pong.py
tools/sharable-ws-filexfer.py
tools/shareable_ws_signaling_serv.py