Metadata-Version: 2.1
Name: onatlib
Version: 0.0.2
Summary: A tool offers P2P communication to transfer files and connect pipes between PCs in different NATs
Home-page: https://github.com/ryogrid/Over-NAT-Lib
Author: Ryo Kanbayashi
Author-email: ryo.contact@gmail.com
License: BSD
Platform: UNKNOWN
Classifier: Development Status :: 3 - Alpha
Classifier: Environment :: Web Environment
Classifier: Intended Audience :: Developers
Classifier: License :: OSI Approved :: BSD License
Classifier: Operating System :: OS Independent
Classifier: Programming Language :: Python :: 3
Classifier: Programming Language :: Python :: 3.7
